{"type":"header","name":"Header","sections":{"header_announcements_9jGBFp":{"type":"header-announcements","disabled":true,"name":"t:names.announcement_bar","settings":{"speed":5,"announcement_bg_color":"#000000","announcement_text_color":"#ffffff","section_width":"page-width","color_scheme":"scheme-1","divider_width":1,"padding-block-start":15,"padding-block-end":15}},"header_announcements_9fk994":{"type":"header-announcements","blocks":{"announcement_nj8bQW":{"type":"_announcement","name":"t:names.announcement","settings":{"text":"Buy 1 Get 10% OFF 😊 | Buy 2 Get 25% OFF 🎉","link":"","font":"var(--font-body--family)","font_size":"0.75rem","weight":"","letter_spacing":"normal","case":"uppercase"},"blocks":{}},"announcement_XDcLiL":{"type":"_announcement","name":"t:names.announcement","settings":{"text":"<strong>Free Shipping 🚚 | Cash on Delivery Available 💵 | 7-Day Easy Returns 🔁<\/strong>","link":"","font":"var(--font-body--family)","font_size":"0.75rem","weight":"100","letter_spacing":"loose","case":"uppercase"},"blocks":{}},"announcement_WxgjPi":{"type":"_announcement","name":"t:names.announcement","disabled":true,"settings":{"text":"Welcome Vibes 🎉 - <strong>10% OFF Sitewide<\/strong>","link":"shopify:\/\/collections\/co-ord-set","font":"var(--font-body--family)","font_size":"0.75rem","weight":"","letter_spacing":"normal","case":"uppercase"},"blocks":{}},"announcement_dMefT3":{"type":"_announcement","settings":{"text":"Shop the New Arrivals","link":"","font":"var(--font-body--family)","font_size":"0.75rem","weight":"300","letter_spacing":"loose","case":"uppercase"},"blocks":{}}},"block_order":["announcement_nj8bQW","announcement_XDcLiL","announcement_WxgjPi","announcement_dMefT3"],"name":"t:names.announcement_bar","settings":{"speed":3,"announcement_bg_color":"#000000","announcement_text_color":"#ffffff","section_width":"page-width","color_scheme":"","divider_width":0,"padding-block-start":10,"padding-block-end":10}},"header_section":{"type":"header","blocks":{"header-logo":{"type":"_header-logo","static":true,"settings":{"hide_logo_on_home_page":false,"padding-block-start":0,"padding-block-end":0,"padding-inline-start":0,"padding-inline-end":0},"blocks":{}},"header-menu":{"type":"_header-menu","static":true,"settings":{"menu":"main-menu","color_scheme":"","type_font_primary_size":"0.875rem","menu_font_style":"regular","type_font_primary_link":"body","type_case_primary_link":"uppercase","menu_style":"collection_images","featured_products_aspect_ratio":"4 \/ 5","featured_collections_aspect_ratio":"16 \/ 9","image_border_radius":0,"navigation_bar":false,"color_scheme_navigation_bar":"","drawer_accordion":true,"drawer_accordion_expand_first":false,"drawer_dividers":true},"blocks":{}},"header-menu-mobile":{"type":"_header-menu","static":true,"settings":{"menu":"main-menu","color_scheme":"","type_font_primary_size":"1rem","menu_font_style":"inverse","type_font_primary_link":"heading","type_case_primary_link":"none","menu_style":"text","featured_products_aspect_ratio":"4 \/ 5","featured_collections_aspect_ratio":"16 \/ 9","image_border_radius":0,"navigation_bar":false,"color_scheme_navigation_bar":"","drawer_accordion":false,"drawer_accordion_expand_first":false,"drawer_dividers":false},"blocks":{}},"header-menu-nav":{"type":"_header-menu","static":true,"settings":{"menu":"main-menu","color_scheme":"","type_font_primary_size":"1rem","menu_font_style":"inverse","type_font_primary_link":"heading","type_case_primary_link":"none","menu_style":"collection_images","featured_products_aspect_ratio":"4 \/ 5","featured_collections_aspect_ratio":"16 \/ 9","image_border_radius":0,"navigation_bar":false,"color_scheme_navigation_bar":"","drawer_accordion":false,"drawer_accordion_expand_first":false,"drawer_dividers":false},"blocks":{}}},"settings":{"logo_position":"center","menu_position":"left","menu_row":"top","show_search":true,"search_position":"right","search_row":"top","show_country":true,"country_selector_style":false,"show_language":true,"localization_font":"heading","localization_font_size":"0.875rem","localization_position":"right","localization_row":"top","section_width":"page-width","section_height":"compact","enable_sticky_header":"always","divider_width":0,"divider_size":"page-width","border_width":0,"color_scheme_top":"scheme-1","color_scheme_bottom":"","color_scheme_transparent":"scheme-6","enable_transparent_header_home":false,"home_color_scheme":"inverse","enable_transparent_header_product":false,"product_color_scheme":"inverse","enable_transparent_header_collection":false,"collection_color_scheme":"default","show_desktop_quick_links":true,"quick_links_bg_color":"#ffffff","quick_links_text_color":"#000000","quick_link_1_text":"Tops","quick_link_1_url":"https:\/\/tsukie.in\/collections\/tops","quick_link_2_text":"Dresses","quick_link_2_url":"https:\/\/tsukie.in\/collections\/dresses","quick_link_3_text":"Skirts","quick_link_3_url":"https:\/\/tsukie.in\/collections\/skirts","quick_link_4_text":"Co-ord Sets","quick_link_4_url":"shopify:\/\/collections\/co-ord-set","social_instagram_link":"https:\/\/www.instagram.com\/tsukieofficial?igsh=aWVscWNvejd5cG5q&utm_source=qr","social_facebook_link":"https:\/\/www.facebook.com\/share\/19xV1AXiJy\/?mibextid=wwXIfr","social_pinterest_link":"https:\/\/in.pinterest.com\/pin\/5207355815244987\/"}}},"order":["header_announcements_9jGBFp","header_announcements_9fk994","header_section"]}