{"sections":{"main":{"type":"product-information","blocks":{"judge_me_reviews_preview_badge_DY3Gkz":{"type":"shopify:\/\/apps\/judge-me-reviews\/blocks\/preview_badge\/61ccd3b1-a9f2-4160-9fe9-4fec8413e5d8","settings":{}},"media-gallery":{"type":"_product-media-gallery","static":true,"settings":{"media_presentation":"grid","media_columns":"one","image_gap":4,"large_first_image":false,"icons_style":"none","slideshow_controls_style":"counter","slideshow_mobile_controls_style":"dots","thumbnail_position":"right","thumbnail_width":44,"enable_color_media_grouping":true,"color_media_group_size":6,"main_media_width":820,"main_media_height":700,"aspect_ratio":"adapt","constrain_to_viewport":false,"media_fit":"contain","media_radius":0,"extend_media":false,"zoom":true,"video_loop":false,"hide_variants":true,"padding-block-start":0,"padding-block-end":0,"padding-inline-start":0,"padding-inline-end":0},"blocks":{}},"product-details":{"type":"_product-details","static":true,"settings":{"width":"fill","custom_width":100,"width_mobile":"fill","custom_width_mobile":100,"height":"fit","details_position":"flex-start","gap":20,"sticky_details_desktop":false,"inherit_color_scheme":true,"color_scheme":"scheme-1","background_media":"none","video_position":"cover","background_image_position":"cover","border":"none","border_width":1,"border_opacity":100,"border_radius":0,"padding-block-start":24,"padding-block-end":24,"padding-inline-start":0,"padding-inline-end":0},"blocks":{"group_icgrde":{"type":"group","name":"Header","settings":{"content_direction":"column","vertical_on_mobile":true,"horizontal_alignment":"flex-start","vertical_alignment":"center","align_baseline":false,"horizontal_alignment_flex_direction_column":"flex-start","vertical_alignment_flex_direction_column":"center","gap":12,"width":"fill","custom_width":100,"width_mobile":"fill","custom_width_mobile":100,"height":"fit","custom_height":100,"inherit_color_scheme":true,"color_scheme":"","background_media":"none","video_position":"cover","background_image_position":"cover","border":"none","border_width":1,"border_opacity":100,"border_radius":0,"toggle_overlay":false,"overlay_color":"#00000026","overlay_style":"solid","gradient_direction":"to top","link":"","open_in_new_tab":false,"placeholder":"","padding-block-start":0,"padding-block-end":0,"padding-inline-start":0,"padding-inline-end":0},"blocks":{"text_xrnftG":{"type":"text","name":"Product title","settings":{"text":"<h1><strong>{{ closest.product.title }}<\/strong><\/h1>","width":"100%","max_width":"normal","alignment":"left","type_preset":"custom","font":"var(--font-heading--family)","font_size":"1.25rem","line_height":"normal","letter_spacing":"normal","case":"uppercase","wrap":"balance","color":"var(--color-foreground-heading)","background":false,"background_color":"#00000026","corner_radius":0,"padding-block-start":0,"padding-block-end":0,"padding-inline-start":0,"padding-inline-end":0},"blocks":{}},"judge_me_reviews_preview_badge_6cehUd":{"type":"shopify:\/\/apps\/judge-me-reviews\/blocks\/preview_badge\/61ccd3b1-a9f2-4160-9fe9-4fec8413e5d8","settings":{}},"price_tVjtKg":{"type":"price","settings":{"discount_badge_bg":"#000000","show_sale_price_first":true,"show_installments":false,"show_tax_info":true,"type_preset":"custom","width":"fit-content","alignment":"left","font":"var(--font-heading--family)","font_size":"1.125rem","line_height":"normal","letter_spacing":"normal","case":"none","color":"var(--color-foreground)","padding-block-start":0,"padding-block-end":0,"padding-inline-start":0,"padding-inline-end":0},"blocks":{}}},"block_order":["text_xrnftG","judge_me_reviews_preview_badge_6cehUd","price_tVjtKg"]},"divider_VJhene":{"type":"_divider","name":"t:names.divider","disabled":true,"settings":{"thickness":1,"corner_radius":"square","width_percent":100,"padding-block-start":0,"padding-block-end":0},"blocks":{}},"trust_badges_3X8bmw":{"type":"trust-badges","name":"Trust Badges","settings":{"icon_size":18,"text_size":10,"alignment":"flex-start","badge_padding_horizontal":0,"badge_padding_vertical":0,"gap_between_badges":6,"block_padding_top":0,"block_padding_bottom":0,"margin_top":0,"margin_bottom":0,"border_radius":6,"background_color":"#dfdfdf","text_color":"#333333","icon_1":"none","icon_svg_1":"","icon_image_1":"shopify:\/\/shop_images\/1-01.png","text_1":"","icon_2":"none","icon_svg_2":"","icon_image_2":"shopify:\/\/shop_images\/1-03.png","text_2":"","icon_3":"none","icon_svg_3":"","icon_image_3":"shopify:\/\/shop_images\/1-02.png","text_3":""},"blocks":{}},"variant_picker_R3rGDr":{"type":"variant-picker","settings":{"variant_style":"buttons","show_swatches":true,"alignment":"left","show_size_guide":true,"size_guide_text":"Size Guide","size_guide_image":"{{ closest.product.metafields.custom.sizechart.value }}","size_guide_left_padding":155,"padding-block-start":0,"padding-block-end":0,"padding-inline-start":0,"padding-inline-end":0},"blocks":{}},"buy_buttons_eYQEYi":{"type":"buy-buttons","settings":{"stacking":true,"show_pickup_availability":false,"gift_card_form":true,"padding-block-start":0,"padding-block-end":0,"padding-inline-start":0,"padding-inline-end":0},"blocks":{"quantity":{"type":"quantity","static":true,"settings":{},"blocks":{}},"add-to-cart":{"type":"add-to-cart","static":true,"settings":{"style_class":"button"},"blocks":{}},"accelerated-checkout":{"type":"accelerated-checkout","static":true,"settings":{},"blocks":{}}},"block_order":[]},"trust_badges_XG6hqp":{"type":"trust-badges","name":"Trust Badges","settings":{"icon_size":36,"text_size":14,"alignment":"center","badge_padding_horizontal":0,"badge_padding_vertical":3,"gap_between_badges":12,"block_padding_top":0,"block_padding_bottom":0,"margin_top":0,"margin_bottom":0,"border_radius":6,"background_color":"#f2f2f2","text_color":"#333333","icon_1":"none","icon_svg_1":"","icon_image_1":"shopify:\/\/shop_images\/1-05.png","text_1":"","icon_2":"none","icon_svg_2":"","icon_image_2":"shopify:\/\/shop_images\/1-04.png","text_2":"","icon_3":"none","icon_svg_3":"","icon_image_3":"shopify:\/\/shop_images\/1-06.png","text_3":""},"blocks":{}},"order_delivery_status_ePTFU7":{"type":"order-delivery-status","name":"Order Delivery Status","settings":{"title":"Order Status","title_weight":"600","subtitle":"Track your delivery and expected arrival time!","subtitle_weight":"400","step_1_title":"Order Confirmed","step_2_title":"On Its Way","step_3_title":"Arriving Soon","title_color":"#1a1a1a","subtitle_color":"#757575","circle_bg_color":"#ffffff","circle_border_color":"#1a1a1a","icon_color":"#1a1a1a","line_color":"#1a1a1a","title_size":12,"subtitle_size":10,"circle_size":26,"icon_size":15,"step_title_size":10,"step_title_weight":"700","step_date_size":10,"step_date_weight":"400","padding_top":0,"padding_bottom":0,"margin_top":0,"margin_bottom":0},"blocks":{}},"custom_liquid_mKP43t":{"type":"custom-liquid","name":"t:names.custom_liquid","disabled":true,"settings":{"custom_liquid":"<div class=\"support-badge\">\n <svg xmlns=\"http:\/\/www.w3.org\/2000\/svg\" xmlns:xlink=\"http:\/\/www.w3.org\/1999\/xlink\" width=\"20\" height=\"20\" viewBox=\"0 0 24 24\" fill=\"none\">\n<mask id=\"mask0_4165_965\" style=\"mask-type:alpha\" maskUnits=\"userSpaceOnUse\" x=\"0\" y=\"0\" width=\"24\" height=\"24\">\n<rect width=\"24\" height=\"24\" fill=\"url(#pattern0_4165_965)\"\/>\n<\/mask>\n<g mask=\"url(#mask0_4165_965)\">\n<rect width=\"24\" height=\"24\" fill=\"#0C3818\"\/>\n<\/g>\n<defs>\n<pattern id=\"pattern0_4165_965\" patternContentUnits=\"objectBoundingBox\" width=\"1\" height=\"1\">\n<use xlink:href=\"#image0_4165_965\" transform=\"scale(0.00195312)\"\/>\n<\/pattern>\n<image id=\"image0_4165_965\" width=\"512\" height=\"512\" preserveAspectRatio=\"none\" xlink:href=\"data:image\/png;base64,iVBORw0KGgoAAAANSUhEUgAAAgAAAAIACAYAAAD0eNT6AAAABHNCSVQICAgIfAhkiAAAAAlwSFlzAAAOxAAADsQBlSsOGwAAABl0RVh0U29mdHdhcmUAd3d3Lmlua3NjYXBlLm9yZ5vuPBoAACAASURBVHic7d13uF5VmbDx+5wkQEISegkE6aCCgKIiCKIwOCIKNlDHNg6WUVHH7lg+EfGzo\/DNDGJhRmwDWEAUQXFAREVBUEFFJfTeSUgv5\/tjnTOGcHLOW\/az1t7vvn\/Xta5YklV2Wft5914FJEmSJEmSJEmSJEmSJEmSJEmSJEmSJEmSJEmSJEmSJEmSJEmSJEmSJEmSJEmSJEmSJEmSJEmSJEmSJEmSJEkaEEOlK6CBsB5wEHAgMAeYBdwDXAucD\/y2XNUkSVLVNgCOA+YDIxOkPwJHYsApSVLj7QPcxsQP\/jXTucCGJSorSZL69xxgMd09\/MfSNcA2+assSZL68RjgAXp7+I+lG4DtM9dbkiT1aBj4Hf09\/MfSPHwTIElSI7yUah7+BgGSJDXIT6k2APBzgCRJNbcxsJzqAwDfBEiSVGNPI+bh75sASSpguHQF1BhbBue\/LXAhBgGSlIUBgDo1kqEMgwBJkmrmAGI\/Afg5QJKkGtqIuEGA46VrcWCgJEm1cBH5AoCxNwHbxTdLkiRNpOqFgAwCJElqgGHgSvIHAX4OkCSpsEfT\/2ZAvgmQJKmBnkveAYG+CZAkqSZeCCzDNwGSJLWOQYAkSS1lECBJUsvMBPYCvkr+AMAxAZLUh6HSFVAjzAT2ID3s9wJ2BXYG5pSs1Kh5wDOAm0tXRJKaxABAa5oC7E5a+38\/YG9gJ+q9cdQ84OnALYXrIUlSYwwBTwD+Ffgh8CBlXuf3m64A1q\/42EiSNFA2Ji3r+xXgDso\/vKtKp1Z5kCRJGgQbA68EzgGWUv5hHZFWkt5mSJLUarOAo4H\/AVZQ\/gGdI329kiMnSVLDDAP7A6cACyj\/QM6dHgDW6fsoStKAcxbA4NiE9Gv\/DbhAzpOAyyvIZwjYE9ge2Ax4iDTT4NfAkgrylySpZ3uRfu0vpPyv77qkI\/o6orAFcAJw61ryfwj4LnBIn+VIktS1Q4ALKf+wrWN6RR\/H9a109+nkSuBlwLQ+ypQkaUJDpK14L6X8Q7bOqZdf5lOA\/+yjzBuBt5MGXkqSVIkh4HnAVZR\/uDYh7dTDMf5URWU\/APwf0vLJkiT17KnAxZR\/qDYl\/bWHY3xYQD3uAN6InwYkSV3aC\/gx5R+oTUvHdXmch4HfBtbnBuB11HsvBUlSDWwMnEh7Fu6pMt03evy68exMdbuM9DZHkqSHmQocA9xL+QdpU9Oruz7q8PmM9VsFnEZas0GSJJ5A2s2u9AO0yenEro968ocCdb0deHGP9ZUkDYDpwLHAMso\/QJucTie9QenF\/QXrfS6u2ihJrfN04FrKPzybnr5OmsPfq9LB10OkQYKSpAE3jfSrfyXlH55NT2fQ+y\/\/MTfVoB0jwHfofgCjJKkhHovf+qtKZ9L\/wx\/gghq0ZSzdSNrJUZI0QI4BFlP+IVNFupm0Gc78QuVX8ct\/zNsKtWFtaQXpDVE\/nzUkSTUwizRIrfSDpdc0H\/gJ8H9JyxFvRXo4nVaoPlX98h8zl7S1b+njvGb6MTC7wnZKkjLaHbiG8g+TbtPvgU8ABzL+w\/bkQvX6NjFL6362UHsmS5cBMwLaK0kK9FJgIeUfIp2kRcDZwOuBR03Srn8uVMfvELeu\/kakPQRKn4fx0leD2ixJqtgQ8BHSqm+lHx4TpVWkTYaOpvNXzXOABwvU9SxgnQ7r2KvdKLsmwETp4MB2S5IqsB5pXnrpB8ZE6Sbg4\/S2Ze7HCtT3XGDdHurai12BP2doU7fposA2S5L6NIf0zbb0w2K8tJL0K\/pA0huKXgwBt2Su9znE\/\/Jf0yzSjoIL+qx7lWkVsH1koyVJvdkZuI7yD4o102LgFNIv2349JnPdf0C+X\/7j2Zz0Kece8rZ7belVsc2VJHVrb+BOyj8gVk93k17zb1VhO5+Xsf7nkz6n1MH6wJspH+B9MrqhkqTOHUy5xXDGSw8CHyA9tKr2j5na8EPq8\/Bf3VTgJcDvKHNuvxDfRElSJ55NfVb2Wwp8Dtg0sL0vzdCOuj78VzcMHAlcT95z\/NkcjZMkTexQ6vHwX0VaFnfH2OYC8OTgtpxH\/R\/+q5tBetuS6w3QO\/I0S5K0Ns8l\/eIu\/fC\/nDT+IJfppK1rI9qSc6pf1bYkz1LP++RqkCTpkQ6j\/MP\/IeDtlNks5r97qO9k6fs09+G\/usOJmyZ5A24OJEnF7EfcL+BO04XALtENncDeVLvC4VkMxsN\/zAbAl6n+vL8tZyMkSX+zN2WWwB1LdwEvC29lZ75CNW36MoP7q\/YFVLd+wJ8YrCBJkhrjMaR59aUe\/j8hrTJYF7OBq+mvTSfQ+4qETTGXdO76OU73k3aUlCRltiXp+2uJB\/8K4IOkaWd1Mwe4iu7btAR4TYH6ljIMvIvexo3cTfrsJEnKbAbwK8o8\/G8GnhbfxL6sD3yRtM9AJ22aR3sfaI8GfkTn5\/8nwA5FaipJLTcMfIsyD\/9ziF3Qp2p7kgKB+xi\/PTcA78Xv2ADPIq3bMN4aEotI5\/7QYrWT1CqD\/h22Vx8H3lOg3E8A7yONtG+aYdKmSNuSdtR7kPTwv7ZgnepqJrAbacOhlcAdpHEVy0pWSpLa7vlUO9Wtk7QceEOOxkmSpEd6NPmn+83H176SJBUzC\/gjeR\/+15GmGUqSpAKGSKvS5Xz4\/5b0DViSJBVyDHkf\/lfQrJH+kiQNnN1IU7ByPfx\/A2ySpWWSJK3F1NIVKGw94BukrW5z+A3wTNKceSnSFOCJpMWXNiMt3HQzcA1poaHF5aomSeWdRL5f\/peQ1tGXIs0krSVxF2u\/FhcC\/0las0GSWudA8s33vwrYME+z1GL7A7fS+XW5GHhrkZpKUiEzgL+S5+F\/C7BNnmapxV5OWkmwl2v0ZFwVVFJLnEieh\/+DwB6Z2qT22p+002I\/12qJpa8lKav96HwHu37SEuDpeZqkFptBesvU7\/W6Anhq5rpLUjZTSAvwRD\/8VwGvyNQmtdv7qO66\/T3ODJI0oN5Knlf\/H87VILXaEHAT1V67b8\/aAknKYAvgfuIf\/j8hvWmQou1N9dfvfGBuzkZIUrTTiH\/430xadEXK4bXEXMdn5GyEJEXai\/iBf8tIo7GlXD5M3PX89xnbIUlhLiD+178Lqii3yADg98BwvqZIUvUOJf7hf1a21kh\/82Zir+uX5WuKJFVrGLiS2E7yfmDrXA2SVnMAsdf29cA62VojSRV6GfG\/\/l+ZrTXSw00FHiD2+n5jttZIUkWGSZvwRHaOP8jWGml8nyH2Gr+NtJWwJDXGi4ntGB\/ATX5U3ubAAmKv9Xdla40k9WkI+B2xneLR2VojTey9xF7rt+BYAEkN8TxiO8Rf4Papqo+ppGl7kdf8y7O1RpL68DPiOsJVuGua6ucA0rUZdd3\/DoNeSTUXsT766unr+ZoideWrxF77B+driiR17xvEdYCLgW3zNUXqypbEDgg8N19TJKk7W5PW5I\/qAI\/P1xSpJ8cRd\/2vAnbO1xRJ6lxk53cHMCtfU6SezALuJO4++Ei+pkhSZ4aBG4nr+N6erylSX95O3H1wMzAlX1MkRRmkUb3PJm5lvvuA7UjfV\/u1AWmDot2AuTRrlbW7gNuBi0lTIVeWrc7\/mkKamXEAMAfYiPQreB5w3uifdbHm+Yc0z\/5qUl0frKCM9YC\/ELdQ1TOBHwflLUld+zZxv3qOraB+2wNfA5YG1jNnuhN4NzC9gmPTq+nAe0iByUR1vYzy+9t3cv6Xkkbyb1dBeW+doJx+09cqqJ8kVWJz4gb\/PQRs0mf93sjgPPjXTPOAx\/V5fHqxJ3Bdl3U9gzJvXLo9\/0uA1\/dZ5gzgni7K7CYtAjbss36SVInIfdFP6LNunw6sW13SAuAZfR6nbhxE79PdriDvw6uf8\/+JPss+vo+yJ0tH9lk3SarEJcR0csuAR\/VRrzcF1auO6V7yTBHbAbi7z7r+iLR8brQqzv8\/91H+5qRf6xHn+\/\/0US9JqsQ2pMFoEZ3cN\/qo13akV7mlH8w50y+JH1haVbD35uB6bkc1538pKejp1ZcqqMN46eQ+6iRJlXgncQ+0g\/qo19cC61Xn9Nw+jtlkDq+wnncRu65Dlef\/tD7q8ZQK67F6+mwfdZKkSlxKTAc3j95\/zW7A4A76myyd3eMx68Q5Fdc1aoe7qs\/\/EmB2H\/W5qsK6jKX39FEfSTUwXLoCfdoceFJQ3qeSOrpePIv27p9+CDFTA2dQ\/WY0h1ec35iqz\/+69DeN8dSqKrKaXwbkKSmjpgcAhxHThlX099p1j6oq0kDTgZ0C8t2Z6gOLqPMUkW8\/eX6VNKC1KncDv6owP0kFDEIAEOGHpCVPezWnqoo01NYBeW4VkGdEPSHm\/PfT\/nuodvGeL5E+cUhqsCYHANNIr5sj\/Fef\/77XTweDImJw3cyG5BmVb7\/H9H3A\/ArqcTvwqQrykVRYkwOA\/ehvYNTaLCGtyd6P26uoiFShO0mrC\/YTnK4AXg3cX0mNJBXV5AAgauW5C0jL\/\/bjqioqIlXsv4F3kMa4dGsl8Erg\/EprJKmYJgcABwbl+70K8vgh1Q66kqryWeD5pJUbO3UTaU2Mb4bUSFIRTQ0A1iUtcFK1EeDcCvKZT9p4Rqqj7wE7Ah8Fbpvg790CvAvYnbQFtKQBkmM99Aj7kvY8r9qvgVsryuuDpA1T1q0oP6lKDwIfIK3pvzewG2nfi6WkVRJ\/DfwRB7RKA6upAcB+QfmeU2FeNwBvIGYRFqkqq4DLRpOkFmnqJ4AnBuXb7+j\/Nf0n8MmK85QkqW9NDQAilv9dCPwuIN\/3kLZ0deEUSVJtNDEA2AKYG5DvpaR5zhFOAXYlLclqICBJKq6JYwCiXv\/\/PCjfMTeS5lEfQ9osZndSIBO1Gl2njixcviSpgCYGAFEbuPwiKN81jU0RrMs0QUd5S1ILNfETwGMC8lxJ+gQgSVIrNDEAeHRAnleT5kVLktQKTQsAhkiD6ap2ZUCekiTVVtMCgK2J2QHwzwF5SpJUW00LAHYKytcAQJLUKk0LAB4VlO81QflKklRLTQsAtgnIcwUwLyBfSZJqywAArgOWBeQrSVJtNS0AiFgC2O\/\/kqTWmWwlwB1Jy9buSFqDf1p4jSb2lIA8bwvIcyIbAIeS9l+fC6yfuXw9XMSKjPsG5FlC3e5\/dW5D0ufNC4F\/AxaXrY6a5FDgctIysYOePlLRMZvM9sDXSJsBlW5zdIrYX+DIGrSrZMq5dHSb7v82pOuI20NFDbbmJ4CZwLeAc4G981eniLszlPFG0kyDlwHrZChP6kUb7\/822B74KfC80hVRvaweAGwE\/Ax4YaG6lBIdAHwa+Hd88Kve2nr\/t8UM4NvAq0tXRPUxFgBMAb4O7FWwLqXcFZj3m4B3BOYvVaHN93+bDANfBl5XuiKqh7EA4M2k735tdE9QvtsBnwnKW6pSm+\/\/thkCTgZeWboiKm+YtLb++0tXpKCoAOB4YN2gvKWqtP3+b6Nh4FQcE9B6w8DzgU1LV6SgiEWANiBmJLxUtbbf\/201BfgmcEDpiqicYeC5pStR2KqAPJ+Fg\/7UDG2\/\/9tsPeBsYPfSFVEZw8AepStR2IqAPNt+TNUcXqvtthFwPrBt6Yoov2FgTulKFBbxBqDtx1TN4bWqrYAfA5uVrojyGiYt\/tFmKwPybPsxfTAgzwUBebbdNLxWlewMfB+XJm+Vpm0GFCHiDUDbReyvkHvPhjaYXroCqpUnA6cz+R4xGhAGAGlerKqzCJgXkO+1uKFJ1QwAtKbDgFOwX2wFAwCYVboCA+bHxDyoFwEXBOTbZjNKV0C19E+kdUw04AwA0raZqs6XAvP+YmDebeQbAK3N+4BjSldCsQwA0qI9qsbFpIFEUc4hbVijavgGQBM5kbRQlAaUAYABQFXuA47OUM6riFu+uW18A6CJDANfA55UuiKKYQBgAFCFBcALSAP1ol1PWmbZaYH9cwlgTWYG8ANgx9IVUfUMAAwA+nUtsB\/w04xlXgQ8lZjZBm0yt3QF1AibkT6\/bVS6IqqWAQBsXroCDXUn8E7gccDVBcq\/irSG+btH66LubVW6AmqMxwBnkhaP0oCIWvDhl8AtAfkeDGxccZ7bV5xflFtIx7WkO0kL8lw8WpfSiygtAT4FnADsCzyNtLTtFiUrNVqXJvy63joo318AtwblrUd6DnnGcxxMWiPgnzKUpUxGAlLUVrjnB9T1RwH1PCOgnmcE1FMxmnL+Lwyo5wjw9IC6au1eRFrSPOJcjpfen6dZita0TwARr3p3CMhTaoKoNwB3BOWr8X0L+EDG8j4CvCJjeQpiAACPwrWv1T5DxAUAdwXlq7X7GHBqprKGSItyHZCpPAUxAEiDWprwvVaq0qOIWQhoKXB\/QL6a3D+Tb7nsdYGzgF0zlacATQsAol4t+hlAbbNHUL53kr4TK7\/lwFHANZnK25i08qfrSTRU0wKA24PyjeoMpbqKuubdtrms+0k7+t2dqbydgLOB9TKVpwo1LQCIWvhl76B8pbraMyhfF2cq7zpSELAoU3n7AafRvOdJ6zXthN1E+sZYtScG5CnVWVQAkGM5aE3uMuAfyfc55kjgo5nKUkWaFgCsIq0FX7VdcUlgtcd04tZ2NwCojzOBD2Us773AGzKWpz41LQCAmA5mCHh8QL5SHe0JTAnK2wCgXo4nvZ7P5STg7zOWpz40cf57VAfzRNImM3W1L+VXA7yLNBDzYtJyryvLVkc9OjAwbwOAehkBXkOa6nxQhvKmkt48HAD8LkN56kMTA4A\/BuW7T1C+VZlL3BLLvbgL+Azw\/4DFheui7jw9KN+7gHuC8lbvlpP6jl8Cu2QobxZp98Cn4KyQWmviJ4DfBuV7MHGvRQfR5sAnSDsBPq5wXdS5qaStlCNcGZSv+ncfcCj5pgduQwoC1s9UnnrQxADgKlJEW7WNcDZAL3YgfQ54RumKqCP7kH6hRTAAqLfrgBcQM5NqPE8ATscfVrXVxABgCfDnoLwdvNKbmaQNSXYuXRFNKjJQMwCov0uAV5FveuBhpDeFqqEmBgAQ19EYAPRuY9Jo46HSFdGEDAB0OmlHv1zeAbwxY3nqkAHAw+1D+hSg3jwFeE7pSmitZhP3\/X8+rgLYJMcCX89Y3onAMzOWpw40NQC4JCjfKaTBgOrda0pXQGt1OGkXtwi\/JC3UpWYYAY4mri9d01TSNObdMpWnDjQ1ALgSWBCU9wuC8m2LQ0grzal+jgrM+2eBeSvGUuB5wF8zlbcB8ANgi0zlaRJNDQBWAJcG5X0EaVCbejOdtEOY6mU2KTiLcnFg3opzL2l6YK71G7YlbSE8I1N5mkBTAwCI+8UxgxQEqHdbl66AHuEI4rZsXUrafEbNNI+80wOfiLsH1kKTT8BPA\/N+WZ\/\/PurzRFO0\/VtwxPmf3+e\/f1EltRjfZaTpuZrYbOCVpCmzfwIeIn2Lr0O6mLjxIeN5Ie4eWFwTlwIe8yvSDRTxuv4QYDN6XzXr9grr0kRtX\/4z4vzf2se\/3YjYKa4\/Ccx7EEwFjgHeD2xauC518l7S+INTS1ekrZr8BmApcR3PVPobMHVVVRVpoEU4HSzi\/F\/dx7\/9R2J\/3Z0TmHfTzQbOAj6LD\/\/xfB74u9KVaLOI10m5Nq15bVD9R+jvm+ZsUoBS+rVeiXRWH8dtUFR9\/pfQ+\/K9Q8A1FdZlzXQ7zf4hEWkmacZS6Xuy7uk+4NE9HmP1oek37g9JF1CEJ9L7oinzKb91bylfKl2BGqj6\/J9O7+MKDgJ2rbAua\/ohjvlYm68Ae5WuRANsRJoeuFnpirRRRESXc9va3wa1YYT+OvHtSL\/cSkfXOVPkwMym2Y5qzv9i4FF91OPbFdRhouS6GeN7NuXvx6alS4ibqaK1iDiROQOA44LaMELadbCfzvfVgXWrW7oX5\/+vqYrz\/7o+yt+adA1HnfPFpM8deqTLKX9PNjF9A\/cTySriJOYMAHYPasNY6ncnq08E168OaT5wYJ\/HaVD1c\/4\/1mfZH+6j7E7Sd\/qs36DakfL3ZJPTcd0fcvUq4gTmDAAgjbqOuhjvBdbvs36vZ3A\/B\/yVFIRp7bo9\/4vpf0+FWaTV3SLP\/Yv7rOOgOoby92WT0yrgFV0fdfUk4gTmDgDeX2Hdx0vHVFDHbUmrXw1KIHAHaZtPv9l1ppPzv4Q0cKyfz05j\/nWCcqpID+FyrmvzGcrfn01PS4CndXvg1Z0h0sGu2lHAmQH5rs1OxG5ocftoGYsqyGs28CzSr+a5NGvfgTtJi\/xcjLu\/9WrN8w9wM2me\/3lUs4rgLOB6YJMK8lqbbwL\/EJh\/k30dj00V7gX2Jd9mRa0UEb3lfgMAaWXAyIj0XfmaIvXlvcT\/Qjs8W2ua5wzK\/4IelPRnYgPZVmv6OgCri15O8j044ln1tz7w9uAy7iDN\/5ei7QJ8l7z7FLTGIAUA3yB9l4yyCfEdq9SvNxO\/oMqXSdMLpRwOAL6A0wNDRLy2KfEJANJFEvk6agGwebbWSN3ZHLif2HtgFWmam9bOTwAx6QPdnARNbpDeAAB8MTj\/mcD7gsuQevUxYMPgMn6Emz2pjOOAl5SuxKCJiNRKvQEA+M0E9aoiLQf2zNYaqTNPBlYS\/yvMpX8n5xuAuLQY2K\/zU6GJDNobAIATg\/OfCpzMYB47NdMwcBLx1+T1wNnBZUgTWY+04+gOpSsyCAbxIfZN0rzqSPsCRweXIXXqVcA+Gcr5LOktg1TSZqTdAzcqXZFBEPGapuQnAEhz9qNfRd2L21eqvI1I0\/JyXO9NWrSqJD8B5EkXANM6PCcaxyC+AQA4BXgwuIyNgU8GlyFN5t+ALTKUczKx02ylbh1M6uvVo6mlKxBkPvAl0lr1kV4FnE5awlXK7UjyLDm7FPj3DOVo7S4FTihdiQ49A3hDprJeTVotsN9dW1sr4tVM6U8AAFsCC4l\/DXXnaFlSTnOI3+1vLEUPrB00EZ8Azsjagv4MkfZDyPUpYBXw0iwtG0CDGgAAfIo8F+APcZUq5fV98lzbi4GtM7VpULQ9AIA0Wv8X5AsCFgNPydKyATPIAcCmpM8BOS7AKrYMljrxevJ1rJ\/K1KZBYgCQbApcS75r9W5cpbJrgxwAAHyUPBffYtIWr1Kk3UmD8XJc0wtwpksvDAD+ZjfgAfIFAVcDG2Rp2QAY1FkAq\/s06QKMth5pDYIZGcpSO21I2hlt\/UzlnUj6VSX16g\/AUcCKTOXtRgqWBnWAe+UG\/Q0AwNvIF4F+C8cDqHrD5PvuP0JaW8Dtr3vjG4BHOpp81+4IaRaYOtCGAGAacA35Lr4P5WmWWuR48nagr87TrIFkADC+T5P3Go6eBj4Q2hAAADyHfBfeKty1StU5gnRN5bp+r6AdnwejGACMbxj4Dvmu45XA87O0rMHaEgAAnE++i28hsHeeZmmA7UFa1TLXdTsCHJClZYPLAGDt1gcuJ9+1\/BD2w2vVtij\/X4BlmcqaQdq1ak6m8jR4diCtMpnzW\/w3gZ9lLE\/tshA4nPgN28asD5wDbJOpvEZpWwDwJ+DjGcubS3rrsEnGMjUYNgPOJW8AeR9pwKwU6TbgUOL3axkzh7RYm9MDx9GmTwAA65CmpuR8pXolbl2pzs0GfkPea3QEB\/5VxU8AnXkWsJx81\/cPcXrgI7QtAIC0ZORK8nauv8DtVDW5dYAfkf\/hfxFOX62KAUDnXkfe6\/wLeZrVHG0MAAA+T\/5O9gLSgkHSeNYFvkf+63IRsHOG9rWFAUB3TiLv9f6WPM1qhrYGALOB68jf2X6f9CtPWt36lPnlPwK8NUP72sQAoDtTyLvI1QrStHDR3gAAYD\/SxZC7w\/0JrrKmv9kAuIQyD\/8f4av\/qhkAdG8m8FvyXfcLgL2ytKzm2hwAAHyEMh3v5cDmGdqnetsY+BVlrsH7cHpUBAOA3mxFmh6Y6\/q\/Fa\/\/1gcAU4FLKdMBz8Nvr222JfB7ylx7I6RNWlQ9A4DePYF8u12OkFa9bPXg7LYHAAC7kH+1tbF0O\/D4+CaqZvYCbqTcw9\/NUuIYAPTneeSdpXU2aRxCKxkAJC8k73rrq6cHgWfGN1E18SLy\/spZM10BTA9vZXsZAPTvHeS9Jz6bp1n1YwDwN7l3q1o9rSKtUti21RnbZAh4D\/nXoFg93UdaYlhxDACq8e\/kvTfelKdZ9WIA8DdTgZ9SrnMeIU2HcdXAwTMT+DZlr61VpNerimUAUI0ppHX8c90fK4DnZmlZjUQcyKYGAJDWjb6Nsh31X0m7wGkwPJayg\/3G0nHRDRVgAFClDYCryXePPAg8LkvLaiLiIDY5AAB4ImnXqpKd9ULgFdENVagh0mvFRZS9lkaAM3G+fy4GANXaDriDfPfKjbRoF9eIA9j0AADgBZT9Vrv6jb9ZcFtVvc0os6zveOly0kqDysMAoHq5f5T9hpbcMxEHbxACAEgDtkp33iPAnaSR42qGZ1L+M9JYuhXYOra5WoMBQIwXkfdH2Tm0YHpgxIEblAAA4IuU78TH0jeBTWObqz5sTLpeSk0nXTM9iGNJSjAAiPOv5L2HPpmnWeVEHLRBCgCmAt+lfGc+lu7AtwF1MwQcDdxN+etjLC0Gnh7YZq2dAUCsU8l7L702T7PKiDhggxQAQNq97zzKd+qrpwtxM4s62BP4OeWvh9XTCtLCVirDACDWNNLW6rnup+XAIVlaVkDEARu0AABgFuU2bZmoo\/8CsEVguzW+DUn7mJfYTXKitBJ4eWC7NTkDgHgbAX8i3331AGk678CJOFiDGAAAbAJcRflOfs30IGnA4rpxTdeomcD7SSvqlT7va6ZVwDFxTVeHDADy2JG8n92uZwB\/bEUcqEENACBN78q5b3U36QbSvPP1ohrfYjOAdwJ3Uf48j5d8+NeHAUA++wNLyHef\/ZIB20cj4iANcgAA6fVv3T4HrJ7uAo4draf6sw7wOtJ0utLndW3Jh3+9GADkdRR5Z96cyQDt2RJxgAY9AID0DarOaY1qjAAAGkVJREFUQcAIcC\/wIdL0NHVnK+DDpO2aS5\/HidJK0gwE1YcBQH4fIu9993\/zNCtexMFpQwAAaZ3qiyn\/EJgsPUSaOrNvzGEYKAcA\/w0so\/x5mywtw+Wi68gAIL8h4Kvkvf9enaVlwSIOTFsCAEjf20vv8tZNuhp4K74VWN1s0lzfuo7tGC8tAJ4VcTDUNwOAMtYl7w+ypcAzsrQsUMSBaVMAAGm5yH+j\/EOhm7QY+Dpp+8s2DhpcH3gJaZGnxZQ\/H92kO4C9qz8kqogBQDmbknZTzXUv3gc8OkvLgkQclLYFAGP+lfosA9tNWkAa2PIPDPbAwemkTZ5Op\/xuj72mvwA7VH1gVCkDgLJ2JY1\/ynVPXkuDl2iPOCBtDQAAXkxzHy4jpNda5wNvJq0j3+TRrlOAJwHvBX5MPbbl7Sf9hLQWherNAKC8p5P6slz35iU09E1qxMFocwAA8HjSntKlHxhVpPtIu2K9mzSIcFqFx6lq65JejR8DfId6LtbTazqJtC+F6s8AoB7+kbz36DdIgxEbJeJAtD0AANgc+CnlHxxVp4XAr0mzCt5JGoi2bUXHrBsbAwcBbwdOA35PM0bud5uW4DS\/pjEAqI+Pkvd+\/XCeZlXDXxRx7gL+DjiBwVqkZQbptfqT1vjf5wN\/Bm4bTXeSBqvdPvqf7x79e\/eP\/rmU9Ep+zCzSK7RZo2k6aXT+lqQAYy6wDfCo0T9nV9imurqF9EnpF6UrIjXUB4CdSIsF5fBB0piAr2Yqr28RUZBvAB7ueeQdlGJqfvoRA7jueEv4BqBe1iMF0bnu3WU0ZHpgkwd4NclZpHEBPy9dEdXeCtJrxGeR3pxI6s8S4HDSL\/McpgHfAnbJVF7PDADyuYkUFX6SNFVQWtO1wH6kfRy8RqTq3AMcQdo5NYeNSYOnaz1rxwAgr+WkbXv3J30vlyC9NvwC6S3RZYXrIg2qP5I+xy7LVN4upIXGartNuwFAGb8kdfafwF96bXcDabDo60l7NkiKcxHwxozlHQD8FzWdHmgAUM5i0gI1B5Hv25TqYxVwMvA44H8K10Vqky8Dn85Y3ktIsxFqKWIUpLMAurMO6dNA09akN\/WWrsSdGQeZswDqb5i0WFiue34V8PIsLeuCbwDqYRnpc8BuwA8K10VxHgD+BXgi6TOQpDJWAS8DfpWpvCHgi6RBvrVhAFAv1wHPAZ6PnwUGyUrSa8ddgRNH\/7ukshaT+tqbM5W3HmlKeG028zIAqKezgMeSBobdUbgu6s8FpP0JXkNaHVJSfdwOHEq+6YGbkd7ybpSpvAkZANTXctLUsJ1IgwUXlK2OunQ5aYDnIcDvCtdF0tr9gTRQb0Wm8h5N+pG3Tqby1soAoP4WksYH7EraV2Bh2epoElcALwCeDFxYuC6SOnMe8LaM5T2NNAuouIgRj84CiLMpaaW4+yk\/mt30t3QF6bqv5XxfZeUsgOY6kbz9xnvzNGvtIhplABBvI9LOU7dT\/uHX1rSK9Mvh4EnOldrFAKC5ppCW8M3Vh6yk8PMyolEGAPmsQzrel1D+gdiWtAA4hTRtU1qTAUCzzSSt1ZGrP1lMwXVBIhpkAFDGPqR9qBdR\/iE5iOlPpO+EG3R6QtRKBgDNNxe4lXx9yx3AdjkatqaIxhgAlDUbeCXwY9Jr6tIPzianB4DTSOv1+31fnTAAGAyPJ73ty9XX\/BHYMEvLVhPREAOA+tgFOJ60+2Dph2lT0mLgbODFpMU7pG4YAAyOI0jf6XP1PecDU7O0bFREIwwA6mk30p4Dl+CbgTXTItLgn1eS3qBIvTIAGCxvJ29f9KU8zUoiGmAAUH87Am8hPfRyvuaqU\/oTcBJp+WV\/6asqBgCD52Ty9k3vzNOsmMobADTLNNLCFB8hvR0Y1F0JbwK+AfwTsE0lR056JAOAwTOVNOU3V1+1krRPQXijpOXAxaMJUkDweOApq6Xty1StZ4tJi\/NcStp571LSqF5J6tYK4Cjg58DuGcobBr4GHEhaVjyEAYDGsxz49Wg6afR\/m03aoOhxo3\/uTlqeeGvKLin9EDCP9Dr\/KtJI2qtJOyuuKlgvSYNlPulz4a+ALTKUNwP4HukH2E0RBRgAqFPzSb+iL13jf59Gep2+7WjaDtgc2Ji0bPHGwCbALNIUl06m0i0mPdjvBe5b7c\/7SDfCjaule3tvkiR15UbgcOAiYHqG8uaQxmntT8CGcAYA6tdy0q\/t67r4N1NJAcGa+TxUVaUkKcivSbOFTifP2889Rss6nIp3LHQ3QJWwgrSZ0erJh7+kpvgW8P6M5R0K\/EfVmRoASJLUvY+T9gTJ5bXAW6vM0ABAkqTevBm4IGN5J5BWJ6yEAYAkSb1ZDryQNPMoh2HSWiZPqiozSZLUm\/mkAXp3ZSpvBnAWFSxmZgAgSVJ\/rgdeACzJVN5WpA3LZvaTiQGAJEn9+znwKtJSvjk8nrRE9JReMzAAkCSpGmcAH85Y3qHAp3v9xwYAkiRV5zjgqxnL+xfgmF7+oQGAJEnVGQGOBi7MWObngOd2+48MACRJqtZy4EXAXzKVNwX4OrBnN\/\/IAECSpOrdBzwbuDtTebOAc4G5nf4DAwBJkmLMIy0UtDRTeWPTA9fv5C8bAEiSFOdnwOszlvcE0u6Bk04PNACQJCnWV4CPZizvMNJmRRMyAJAkKd4HSQP1cnkn8IaJ\/oIBgCRJ8UaA1wC\/yFjmScAha\/s\/p2asiCR1a3NgB2ALYJ0O\/80y4E7gOvJt0BJtG+DI0pVQJcZ285uWoaypwJnAU4E\/jPcXRgKSF6qkXq0PvBv4DbCK3vuhVcDlwLvocFR0Rc7oo84mU0S6nhREP0JEYQYAknrxYuB2qu+TbiNfv2QAYKpjuoy0lfD\/cgyApLr4KPBNYMuAvOeQpkZ9JCBvqQmeCJzGas99AwBJdfBe4H3AUGAZQ8AHSJ8EpDZ6IXD82H8xAJBU2oHknSP9MeCAjOVJdfJe4KVgACCprCHSgiU5+6IpwGeIfdsg1dUQcAIwzQBAUkkHAU8pUO6TgKcXKFeqgy2B\/QwAJJX0vIJlH1GwbKm0xxgASCpp\/4JlP61g2VJp2xgASCqp473LA2xdsGypNAMASUXNKlj2BkH5Lg\/KV6qSAYCkou4sWPbtDctXqtIGBgCSSrp+AMu+IShfqUrTDQAklfTDgmWfG5Tv94Pylaq0ngGApJK+DawsUO4K4DtBed9A2oVQqjMDAElFXQv8V4FyvwxcF5j\/BwLzlqpgACCpuA+Sd+DcbcCHgss4HzgzuAypHwYAkoq7HXg+sDhDWYtJqw\/mmH3wauDKDOVIvVjXAEBSHfwKeCpwc2AZt5HW\/78ssIzVLSTtdXB+pvKkbgwZAEiqiyuBJwNfotqBgSuALwBPAH5dYb6deAA4DHgLcHfmsqUJDQEjAfkehd+\/JPVuB+BFwLOAHUm7l63T4b9dBtwBzAPOA75F7IC\/Ts0ibUB0BLAbsA0ws2iN1HojAenIrC2QJGlwHUnAs9pPAJIktZABgCRJLWQAIElSCxkASJLUQgYAkiS1kAGAJEktZAAgSVILGQBIktRCBgCSJLWQAYAkSS1kACBJUgsZAEiS1EIGAJIktZABgCRJLWQAIElSCxkASJLUQgYAkiS1kAGAJEktZAAgSVILGQBIktRCU0tXQJKkBpsCPBU4AJgDbB5QxtyAPA0AJEnqwXTgLcA7gM0K16UnBgCSJHVnT+C7wPalK9IPAwBJkjp3EHA2MLN0RfrlIEBJkjqzA3A6A\/DwBwMASZI6dRqwaelKVMUAQJKkyR1OGu0\/MAwAJEma3GtLV6BqBgCSJE1sBnBw6UpUzQBAkqSJ7USa9z9QDAAkSZrY1qUrEMEAQJKkiY2UrkAEAwBJkiZ2W+kKRDAAkCRpYtcCi0tXomoGAJIkTWwRcEHpSlTNAECSpMl9sXQFqmYAIEnS5M4Bfla6ElUyAJAkqTOvAu4pXYmqGABIktSZ64EjgQWlK1IFAwBJkjp3EWlToHmF69E3AwBJkrpzFbA78G7gzsJ16dkQMSscnQBcGpBvp5aRTsp1wF0F6xFtOrADMBOYNfrnuqN\/zgcWAkuAB0nfrW4BVhapqaRBY\/+TTAH2BZ4GzAG2CChj7mgZlYoKAOpiBLgCOB34D9IF2UQzgL1JF8DjSDfd9qSLrRvLgJtIgdF1wGWkQO0aYFVVlZU0UOx\/yjsSOCMi45GWpNtIB7EJppK2nvwccDmwnNhjcz9wHvAeYJcM7ZNUX\/Y\/9XMkMce++IM5Z1oFfKTLA5\/LOsDzgK8A91L2OP0B+Cjw+NAWS6oL+596MwCoML2ru2MfamtS5Hsz5Y\/LeOly4HXA+lEHQFIx9j\/NYABQYVoBHNDV4a\/e04DvkwbFlD4enaT7SYM7t4o4GJKysv9pFgOAitOvSYMgc9uHtKRk6fb3mpYCpwBbVn1gJIWz\/2kmA4CA9IxuzkCfHkOzb7w10wLgeHw1JzWB\/U+zGQAEpM91cwZ6NI30jW1JgfblSLcAL6jsaEmqkv3PYDAACEhXdHMGenAQ8OcatDNHOoPu5wVLimP\/MzgMAAJS1BKOU4Fjac4Am6rSPcBh\/R8+SX2w\/xk8BgABaUk3Z6BDjwJ+UYO2lUqrgE+QOiFJedn\/DGb\/YwAQkG7o4gR04lBSFFq6XXVIl9DeKTtSCfY\/g9v\/GAAEpP\/p5gxM4rXEL5nZtHQDafSxpFj2P4Pd\/xgABKR3dnMG1mKI9L2tdFvqmu4jLToiqXr2P+3ofwwAKk7LSbta9WMKcGoN2lL3tBg4osdjLGl89j\/t6X8MACpOn+\/q8D\/S0GgepdvRlLSMwR2hK+Vm\/9Ou\/scAoMJ0K7BFV4f\/kU6oQTualhYBB\/ZysCU9jP1Pu\/ofA4CK0iLgSd0d+0c4tgbtaGqaDzy56yMuacyxlL+Pm5qa2v8YAFSQbqX\/k\/\/yGrSj6ekOYG63B16S\/U8FqYn9jwFAH2k5aQepfl\/77016g1C6PYOQfgWs193hl1rN\/qe9\/Y8BQBdpKXAjaZ7\/u+l\/tD\/A5qN5lm7bIKVTuzoDUnvZ\/7S7\/wkJAKKWSzwKODMo7xKGgW+Sltmsg0XAZaPpT8A1wF2jaf7o31kX2ADYBNge2BHYi\/QJ5LGkNpX2auBS4AulKyLVmP1PDPsfYiKrI7O2IN6bKR+t3kAa+XsgaYvPfmwGvIwUpC0u3K4FpA5C0vjsf+x\/GvUJYJACgB2Bhyhzca4Evg08k7iIeSPgjZTdNvR\/SPOaJT2c\/Y\/9DxgAFDEM\/JQyN97XyLuO9TDwfODqCtvRTXpTfBOlRrH\/sf8ZYwBQwGvIfyH+gv7XKejHFOB15N9VbAEwJ0P7pKaw\/7H\/GWMAkNlM4DbyXYCLgH+hHoNjIE2ZPJO8N2GrB+NIq7H\/sf9ZnQFAZseS78K7hjQyto5eR76BOiuA3fI0S6q1Y7H\/AfufMQYAGW1FvoE355Cmy9TZ3uT7NfKDTG2S6sr+5+HsfwwAsjqJPBfbfwFRazFUbTvSnN8cx2XfPE2Sasn+55G2o939jwFAJhuSBoREX2QnU\/+pJ2vakvS6MPrYDNIiUlI37H\/Wrs39jwFAJu8i\/gL7OvUZbNOtrUmLgkQenxU0Y3EOqWr2PxNra\/9jAJDBNOAmYi+ui+h\/Ja3SHkda8jPyOH02W2ukerD\/6Uwb+x8DgAxeROxFdRNpU49B8HxgFXHH6kFgRrbWSOXZ\/3Subf1PSADQ1NdAUf4hMO9VwCtIG2YMgu+SviNGmQ08JzB\/qW7sfzpn\/1ORiOipiW8AZhM73\/TT+ZqSzXTgr8Qds+\/ka4pUlP1P99rU\/\/gJINiriLuQbgbWz9eUrA4h7rgtpv5zlKUq2P\/0pi39j58Agh0VmPe7gIWB+Zf0Y+CsoLzXA44IyluqE\/uf3tj\/9CkicmraG4B1SDdIxLG4kubNt+3WbqQdxCKO31cztkMqwf6nP23of3wDEOjJxI34PJ50sAfZH0j7hkd4RlC+Ul3Y\/\/TH\/qdHBgDJgUH5XkcardoGJwXluzWwc1DeUh3Y\/\/TP\/qcHBgBJ1A34ZdL0mza4BPh9UN5R50eqA\/uf\/tn\/9GCImNdDvwRuCcg3ynNIU0qqNAI8ijzHYQrwVOAAYA6wEXAnMA84b\/TPHN4NfCIg378Cvw3IV6oD+59qDHL\/M5egTYoiBk6Y4NJuTkKPpgPvIS3uMVFdLgP+PkN9tp2kHiaTKU+y\/zF1kopXYFDT+4i1J+kbXzd1OoP4+cB\/7LJOJpOp+mT\/Y5o0OQYgzs8C8z6I9M2r2x2rjiTVa8PKa\/Q3FwTmLakz9j+alAFAjGWk114RdgBOB2b2+O8fT4rEp1ZWo4f7VVC+kjpj\/6OOGADEuAZYEpT3acCmfeZxCPCGCuoyniuD8pXUGfsfdcQAIMafgvI9nDTatgofBGZVlNfq\/gKsCMhXUmfsf9QRA4AY1wfl+9oK89qMmHWuVwC3B+QrqTP2P+qIAUCMiD23ZwAHV5zn4RXnN6ZJa0BIg8b+Rx0xAIhxb0CeO1P9YiF7VJzfmAVB+UqanP2POmIAEGN5QJ5bBeS5dUCeAIuC8pU0OfsfdWQYo6UIKwPyHAnIM2qdcANLqRz7H3ViwTAOmIgQsdrVbQF53hqQJ8DsoHwlTc7+R524ZRi4qnQtBlDESlfXAosrzvPqivMb0+siIZL6Z\/+jTlw9DJxduhYDaIuAPBdR\/TKXZ1Wc35h+FwqR1Dv7H3Xi7GHSSbi7dE0GzA5B+X6xwrzuAr5XYX5jppO2IZVUhv2PJnMXowHAAuD4wpUZNLsE5XsO1W3ycRzwUEV5rW5nHIQjlWT\/o8k87PhPAc6jBtsTDkhaRvVzZsdsT3pj00\/9zied8wgv7bNuJpOpv2T\/Y5ooncvo8R+LlFYCL8GNFKoyDXhCUN7Xk7bV7HX65m+Ao4iZKgRwYFC+kjpj\/6O1+Q0pSFoJD39V8gBwAHBmgUoNor8LzPsi0qYc87r8d\/8NPA14sOoKreagwLwldcb+R2vq+Pg\/k7SvculXFU1OOfalXg94F3DHJHW5lLQFZ7TtJ6mHyWTKk+x\/TJMe\/6EODuihwI6kqSXrTPL3m+o5VP\/NbBXpuN1Qcb7jmQLsS4ru5gAbkW7KeaSxHddnqAPA+4CPBuT7V+C3AflKdWD\/Uw37n2QZZY5\/Y\/2ImMjrgzkbUQNXE3McX5OzEVJm9j\/VsP9RT95HzIVzPTA1YztK2pe4V1g7ZWyHlJv9T\/\/sf9Sz\/Ym7eF6csR0lnU3M8YtaL1yqC\/uf\/tn\/qGfrAAuJuYCuYPAXptiD9M0x4vh9LWM7pBLsf\/pj\/6O+\/YC4KPzlGdtRwveIO3avyNgOqRT7n97Z\/6hvryDuIrqRmC066+A5xB23xbi1p9rB\/qc39j+qxGzSCY+6mD6XrynZTAeuI+6YfTtfU6Si7H+6Z\/+jSn2LuItpJWmlxUFyCnHHa4S05KjUFvY\/3bH\/UaVeSOwFdSsxe3WXEL3pxoPEbWgi1ZH9T+fsf1S5qaTvZZEX1oU0f0XFPYD5xB6nz2RrjVQP9j+dsf9RmHcSe2GNkDZlaOrUnG2Am4g9PitIy1BLbWP\/MzH7H4XakPjocgQ4mebdhFsCfyb+2Jyeq0FSzdj\/rJ39j7L4HPEX2QhwKs1ZqnNn0uYSOY7LPpnaJNWR\/c8j2f8omy2BBeS52M4DNsjTrJ7tA9xJnuNxTqY2SXVl\/\/Nw9j\/K7kPkueBGgD8Be+ZpVleGgLcAS8lzHJYDj83SMqne7H\/sf1TQ+qRpM7luwsXA20h7a9fBlsB3ydf+EeDzWVom1Z\/9j\/2PCjuavBfgCHA58KQcjVuLKaSo+wHytns+6aaXlNj\/2P+ooGHgIvLfhKuAM4HHhLfwb6aQFte4usJ2dJPeEN9EqVHsf+x\/VNgO5BuQs2ZaSdol7FnEvZrbBHgT8JdCbRwBLiB975P0cPY\/9j8q7I2UuzjH0m3AZ4GDgPX6bM9WpN3HziLfAJu1pfnAtn22Rxpk9j\/2PyGMejozBJwPHFK6IqMWA78GrgR+D1wP3ALcO\/r\/LQE2AmaOpl2AXUfTfsCj81d5rV4DfLl0JaQas\/+JY\/+jjmxMvoUo2pK+0tUZkNrL\/sf+R4XtCSyk\/IU7COmXwLrdHX6p1ex\/7H9U2D9Q\/uJteroDmNvtgZdk\/1NBsv8ZVZdFH5rkKtJF9IzSFWmo+aRRxdeUrojUQPY\/\/bH\/USU+TvlItmlpIXBgLwdb0sPY\/9j\/qKAh4D8of1E3JS0FDu3pSEtak\/2P\/Y8KGwZOofzFXfe0EDisx2MsaXz2P\/Y\/qoH3kJbPLH2h1zHdC+zf+6GVNAn7H\/sfFfYqYBnlL\/g6peup16If0qCy\/7H\/UWF\/D9xN+Qu\/DulnwJz+DqekLtj\/2P+osLmki6\/0DVAqrQJOBKb1eyAldc3+x\/5HhU0FjiXtplX6hsiZ7gae3f\/hk9QH+x+pBvYH\/kD5GyNHOgfYuprDJqkC9j9SYdNIo3QXU\/4miUjXkVbWklQ\/9j9SDexC2v96UKbrzCe9ZpxR4TGSFMP+R6qBPYAzKH8D9ZoWkgbZbFH1gZEUzv5HqoGnkiLyFZS\/qTpJ9wCfxBtPGgT2P1INbEX6RncT5W+y8dLlwOvwVZs0iOx\/pBqYBhwOnEr5xTyuAj4C7BnaYkl1Yf\/TQkOlK6BxTQEOAJ5LelX3BGIXtrgPuBS4kPRa8NrAsiTVm\/1PSxgANMN6wN7AU0iDeHYYTXPo7hwuBW4kTZ2ZR3q9dinwZ1LkLUlrsv8ZUAYAzbYesD0wE9iA9J1sOrA+sAB4iDT\/dwFwF3AraRqQJPXL\/keSJEmSJEmSJEmSJEmSJEmSJEmSJEmSJEmSJEmSJEmSJEmSJEmSJEmSJEmSJEmSJEmSJEmSJEmSJEmSJEmSJEmSJEmSJEmSJEmSJEmSJEmSJEmSJEmSJEmSJEmSJEmSJEmSJEmSJEmSJEmSJEmSJEmSJEmSJEmSJEmSJEmSpEr9f8BZn+niPYgSAAAAAElFTkSuQmCC\"\/>\n<\/defs>\n<\/svg>\n  <span>Shipped in 24 Hours<\/span>\n<\/div>\n\n<style>\n.support-badge {\n  display: flex;\n  align-items: center;\n  justify-content: center;\n  gap: 8px;\n  color: #000;\n  padding: 4px 8px;\n  border-radius: 4px;\n  font-size: 10px;\n}\n\n.support-icon {\n  width: 12px;\n  height: 12px;\n}\n<\/style>"},"blocks":{}},"custom_liquid_ywreAP":{"type":"custom-liquid","name":"t:names.custom_liquid","disabled":true,"settings":{"custom_liquid":"<div class=\"delivery-message\">\n  <p class=\"delivery-text\">\n    <img \n      src=\"https:\/\/cdn-icons-png.flaticon.com\/512\/679\/679720.png\" \n      alt=\"Delivery Icon\" \n      class=\"delivery-icon\"\n    \/>\n    Estimated delivery : <span id=\"deliveryDate\"><\/span>\n  <\/p>\n<\/div>\n\n{{ '\/\/cdnjs.cloudflare.com\/ajax\/libs\/datejs\/1.0\/date.min.js' | script_tag }}\n\n<style>\n  .delivery-message {\n    text-align: center;\n    width: 100%;\n    padding: 12px;\n    background: #f2f2f2;\n  }\n\n  .delivery-text {\n    font-size: 10px;\n    font-weight: 500;\n    display: flex;\n    align-items: center;\n    justify-content: center;\n    gap: 4px;\n  }\n\n  .delivery-icon {\n    width: 20px;\n    height: 20px;\n  }\n\n  #deliveryDate {\n    font-weight: 600;\n  }\n<\/style>\n\n<script>\n  \/\/ --- Delivery Date Logic ---\n  const today = new Date();\n  \n  \/\/ Clone 'today' for each calculation, as .addDays() modifies the date object.\n  let minDeliveryDate = new Date(today).addDays(4);\n  let maxDeliveryDate = new Date(today).addDays(7);\n\n  \/\/ Format the dates\n  const minDateStr = minDeliveryDate.toString('ddd, d MMM');\n  const maxDateStr = maxDeliveryDate.toString('ddd, d MMM');\n\n  \/\/ Display delivery date range\n  document.getElementById('deliveryDate').innerHTML =\n    minDateStr + ' - ' + maxDateStr;\n<\/script>"},"blocks":{}},"custom_liquid_CUJWG6":{"type":"custom-liquid","name":"t:names.custom_liquid","disabled":true,"settings":{"custom_liquid":"{% comment %} --- START: SVG Feature Icons (Flexbox Center) --- {% endcomment %}\n<style>\n  .svg-feature-icons-wrapper {\n    display: flex;\n    justify-content: space-between;\n    align-items: flex-start;\n    gap: 15px;\n    padding: 0;\n    margin-top: 2px;\n    color: #121212; \n  }\n  \n  .svg-feature-icon-col {\n    flex: 1; \n    min-width: 0;\n    display: flex;\n    flex-direction: column;\n    align-items: center;\n    text-align: center;\n  }\n  \n  .svg-feature-icon-col svg {\n    width: 22px;\n    height: 22px;\n    stroke: #777;\n    margin-bottom: 8px; \n  }\n  \n  .svg-feature-icon-heading {\n    font-family: 'Josefin Sans', sans-serif;\n    font-weight: 500;\n    font-size: 0.8rem; \n    margin: 0 0 3px 0; \n    word-wrap: break-word;\n  }\n  \n  .svg-feature-icon-subheading {\n    font-family: 'Roboto', sans-serif;\n    font-size: 0.7rem; \n    color: #555; \n    margin: 0;\n    word-wrap: break-word;\n  }\n<\/style>\n<div class=\"svg-feature-icons-wrapper\">\n  \n  <div class=\"svg-feature-icon-col\">\n    <svg xmlns=\"http:\/\/www.w3.org\/2000\/svg\" fill=\"none\" viewBox=\"0 0 24 24\" stroke=\"currentColor\" stroke-width=\"1.5\">\n      <path stroke-linecap=\"round\" stroke-linejoin=\"round\" d=\"M20 7l-8-4-8 4m16 0l-8 4m8-4v10l-8 4m0-10L4 7m8 4v10M4 7v10l8 4\" \/>\n    <\/svg>\n    <h4 class=\"svg-feature-icon-heading\">Free shipping<\/h4>\n  <\/div>\n  \n  <div class=\"svg-feature-icon-col\">\n    <svg xmlns=\"http:\/\/www.w3.org\/2000\/svg\" fill=\"none\" viewBox=\"0 0 24 24\" stroke=\"currentColor\" stroke-width=\"1.5\">\n      <path stroke-linecap=\"round\" stroke-linejoin=\"round\" d=\"M4 4v5h.582m15.356 2A8.001 8.001 0 004.582 9m0 0H9m11 11v-5h-.581m0 0a8.003 8.003 0 01-15.357-2m15.357 2H15\" \/>\n    <\/svg>\n    <h4 class=\"svg-feature-icon-heading\">Easy Exchange<\/h4>\n  <\/div>\n  \n  <div class=\"svg-feature-icon-col\">\n    <svg xmlns=\"http:\/\/www.w3.org\/2000\/svg\" fill=\"none\" viewBox=\"0 0 24 24\" stroke=\"currentColor\" stroke-width=\"1.5\">\n      <path stroke-linecap=\"round\" stroke-linejoin=\"round\" d=\"M3 5a2 2 0 012-2h3.28a1 1 0 01.948.684l1.498 4.493a1 1 0 01-.502 1.21l-2.257 1.13a11.042 11.042 0 005.516 5.516l1.13-2.257a1 1 0 011.21-.502l4.493 1.498a1 1 0 01.684.949V19a2 2 0 01-2 2h-1C9.716 21 3 14.284 3 6V5z\" \/>\n    <\/svg>\n    <h4 class=\"svg-feature-icon-heading\">24x7 Customer Care<\/h4>\n  <\/div>\n  \n<\/div>\n{% comment %} --- END: SVG Feature Icons (Flexbox Center) --- {% endcomment %}"},"blocks":{}},"accordion_b7Ch4G":{"type":"accordion","name":"t:names.accordion","settings":{"icon":"caret","dividers":true,"type_preset":"h6","inherit_color_scheme":true,"color_scheme":"","border":"none","border_width":1,"border_opacity":100,"border_radius":0,"padding-block-start":0,"padding-block-end":0,"padding-inline-start":0,"padding-inline-end":0},"blocks":{"accordion_row_NVj9W9":{"type":"_accordion-row","settings":{"heading":"Product Description","content":"","heading_font_size":18,"open_by_default":false,"open_by_default_desktop":true,"icon":"none","width":20},"blocks":{"text_48wnPy":{"type":"text","settings":{"text":"<p><\/p>{{ closest.product.description }}","width":"100%","max_width":"normal","alignment":"left","type_preset":"custom","font":"var(--font-body--family)","font_size":"0.875rem","line_height":"normal","letter_spacing":"normal","case":"none","wrap":"pretty","color":"var(--color-foreground)","background":false,"background_color":"#00000026","corner_radius":0,"padding-block-start":0,"padding-block-end":0,"padding-inline-start":0,"padding-inline-end":0},"blocks":{}}},"block_order":["text_48wnPy"]},"accordion_row_AkDPD9":{"type":"_accordion-row","settings":{"heading":"Specifications","content":"{{ closest.product.metafields.custom.fit_and_style_new | metafield_tag }}","heading_font_size":18,"open_by_default":false,"open_by_default_desktop":false,"icon":"none","width":20},"blocks":{"text_EFA3zK":{"type":"text","settings":{"text":"<p>{{ closest.product.metafields.custom.fabric_fit_and_style | metafield_tag }}<\/p>","width":"100%","max_width":"normal","alignment":"left","type_preset":"rte","font":"var(--font-body--family)","font_size":"1rem","line_height":"normal","letter_spacing":"normal","case":"none","wrap":"pretty","color":"var(--color-foreground)","background":false,"background_color":"#00000026","corner_radius":0,"padding-block-start":0,"padding-block-end":0,"padding-inline-start":0,"padding-inline-end":0},"blocks":{}}},"block_order":["text_EFA3zK"]},"accordion_row_kc66Nb":{"type":"_accordion-row","settings":{"heading":"Care","content":"{{ closest.product.metafields.custom.fabric_care_new | metafield_tag }}","heading_font_size":18,"open_by_default":false,"open_by_default_desktop":false,"icon":"none","width":20},"blocks":{"text_Mcmdzh":{"type":"text","settings":{"text":"<p>{{ closest.product.metafields.custom.fabric_care | metafield_tag }}<\/p>","width":"100%","max_width":"normal","alignment":"left","type_preset":"rte","font":"var(--font-body--family)","font_size":"1rem","line_height":"normal","letter_spacing":"normal","case":"none","wrap":"pretty","color":"var(--color-foreground)","background":false,"background_color":"#00000026","corner_radius":0,"padding-block-start":0,"padding-block-end":0,"padding-inline-start":0,"padding-inline-end":0},"blocks":{}}},"block_order":["text_Mcmdzh"]}},"block_order":["accordion_row_NVj9W9","accordion_row_AkDPD9","accordion_row_kc66Nb"]},"available_benefits_W3igGX":{"type":"available-benefits","name":"Available Benefits","settings":{"title":"SPECIAL OFFERS","block_border_color":"#1a1a1a","card_bg_color":"#f4f4f4","border_color":"#b0b0b0","code_color":"#0037fe","title_color":"#1a1a1a","main_text_color":"#000000","desc_text_color":"#000000","tc_text_color":"#333333","title_size":14,"title_weight":700,"main_text_size":13,"desc_text_size":12,"tc_text_size":12,"block_border_thickness":1,"block_padding":12,"block_border_radius":0,"card_width":150,"card_height":0,"card_border_radius":0,"card_padding_horizontal":10,"card_padding_vertical":0,"gap_between_cards":10,"margin_top":0,"margin_bottom":0,"prefix_1":"Use Code","code_1":"TSUKIE25","desc_1":"Buy 2 Get 25% Off","tc_link_1":"","prefix_2":"Use Code","code_2":"TSUKIE10","desc_2":"Buy 1 Get 10% Off","tc_link_2":"","prefix_3":"","code_3":"","desc_3":"","tc_link_3":""},"blocks":{}},"style_it_with_cmztVr":{"type":"style-it-with","name":"Style it with","settings":{"heading":"STYLE IT WITH","split_title":true,"show_arrow":true,"product_list":"{{ closest.product.metafields.custom.style_it_with.value }}","metafield":"","max_products":4,"card_width":110,"columns_gap":8,"image_ratio":"4\/5","title_size":14,"title_size_mobile":14,"title_weight":"500","price_size":11,"price_size_mobile":14,"margin_top":0,"padding_top":0,"padding_bottom":0},"blocks":{}}},"block_order":["group_icgrde","divider_VJhene","trust_badges_3X8bmw","variant_picker_R3rGDr","buy_buttons_eYQEYi","trust_badges_XG6hqp","order_delivery_status_ePTFU7","custom_liquid_mKP43t","custom_liquid_ywreAP","custom_liquid_CUJWG6","accordion_b7Ch4G","available_benefits_W3igGX","style_it_with_cmztVr"]}},"block_order":["judge_me_reviews_preview_badge_DY3Gkz"],"settings":{"content_width":"content-center-aligned","desktop_media_position":"left","equal_columns":false,"limit_details_width":false,"gap":48,"color_scheme":"","padding-block-start":0,"padding-block-end":0,"padding_inline_start":100,"padding_inline_end":0}},"blocks_PzEKUJ":{"type":"_blocks","blocks":{"ai_gen_block_b1bef95_yJtVxb":{"type":"ai_gen_block_b1bef95","settings":{"end_date":"2026-06-10","end_time":"23:59:59","show_days":true,"show_hours":true,"show_minutes":true,"show_seconds":true,"offer_text":"Buy 2 Get 25% | Limited Time Offer","offer_text_size":24,"offer_text_color":"#000000","offer_spacing":8,"number_size":24,"number_color":"#000000","number_background":"#f5f5f5","number_padding":12,"number_min_width":48,"number_border_radius":8,"days_label":"Days","hours_label":"Hours","minutes_label":"Minutes","seconds_label":"Seconds","label_size":14,"label_color":"#000000","label_transform":"none","label_spacing":8,"timer_gap":8,"unit_width":60,"max_width":1200,"padding_top":16,"padding_bottom":16,"padding_horizontal":20,"background_color":"#ffffff","expired_message":"This offer has ended","expired_text_size":20,"expired_text_color":"#666666"},"blocks":{}}},"block_order":["ai_gen_block_b1bef95_yJtVxb"],"name":"Countdown timer","settings":{"content_direction":"column","vertical_on_mobile":true,"horizontal_alignment":"flex-start","vertical_alignment":"center","align_baseline":false,"horizontal_alignment_flex_direction_column":"center","vertical_alignment_flex_direction_column":"center","gap":0,"section_width":"page-width","section_height":"","section_height_custom":50,"color_scheme":"scheme-5","background_media":"none","video_position":"cover","background_image_position":"cover","border":"none","border_width":1,"border_opacity":100,"border_radius":0,"toggle_overlay":true,"overlay_color":"#ffffff","overlay_style":"solid","gradient_direction":"to top","padding-block-start":0,"padding-block-end":0}},"17764266138876d846":{"type":"_blocks","blocks":{"judge_me_reviews_review_widget_yTKpAq":{"type":"shopify:\/\/apps\/judge-me-reviews\/blocks\/review_widget\/61ccd3b1-a9f2-4160-9fe9-4fec8413e5d8","settings":{"review_data":"real_data","max_width":1200,"show_shop_reviews":false,"empty_state":"empty_widget"}}},"block_order":["judge_me_reviews_review_widget_yTKpAq"],"settings":{"content_direction":"column","vertical_on_mobile":true,"horizontal_alignment":"flex-start","vertical_alignment":"center","align_baseline":false,"horizontal_alignment_flex_direction_column":"flex-start","vertical_alignment_flex_direction_column":"center","gap":12,"section_width":"page-width","section_height":"","section_height_custom":50,"color_scheme":"","background_media":"none","video_position":"cover","background_image_position":"cover","border":"none","border_width":1,"border_opacity":100,"border_radius":0,"toggle_overlay":false,"overlay_color":"#00000026","overlay_style":"solid","gradient_direction":"to top","padding-block-start":0,"padding-block-end":0}},"1777368950ce942549":{"type":"_blocks","blocks":{"ai_gen_block_78e2178_A9Cknj":{"type":"ai_gen_block_78e2178","name":"Title block","settings":{"heading":"Shop the Vibe","font_size":24,"font_size_mobile":16,"text_transform":"uppercase","letter_spacing":0,"alignment":"center","text_color":"#ffffff","background_color":"#000000","padding_top":12,"padding_bottom":12,"padding_horizontal":0,"padding_top_mobile":12,"padding_bottom_mobile":12,"padding_horizontal_mobile":12},"blocks":{}}},"block_order":["ai_gen_block_78e2178_A9Cknj"],"disabled":true,"settings":{"content_direction":"column","vertical_on_mobile":true,"horizontal_alignment":"flex-start","vertical_alignment":"center","align_baseline":false,"horizontal_alignment_flex_direction_column":"flex-start","vertical_alignment_flex_direction_column":"center","gap":12,"section_width":"page-width","section_height":"","section_height_custom":50,"color_scheme":"","background_media":"none","video_position":"cover","background_image_position":"cover","border":"none","border_width":1,"border_opacity":100,"border_radius":0,"toggle_overlay":false,"overlay_color":"#00000026","overlay_style":"solid","gradient_direction":"to top","padding-block-start":0,"padding-block-end":0}},"product_recommendations_qggXJq":{"type":"product-recommendations","blocks":{"ai_gen_block_78e2178_jxW8zL":{"type":"ai_gen_block_78e2178","name":"Title block","settings":{"heading":"You may also like","font_size":24,"font_size_mobile":16,"text_transform":"uppercase","letter_spacing":0,"alignment":"center","text_color":"#ffffff","background_color":"#000000","padding_top":12,"padding_bottom":12,"padding_horizontal":0,"padding_top_mobile":12,"padding_bottom_mobile":12,"padding_horizontal_mobile":12},"blocks":{}},"text_cbcgyb":{"type":"text","name":"t:names.header","disabled":true,"settings":{"text":"<h3>You may also like <\/h3>","width":"fit-content","max_width":"normal","alignment":"left","type_preset":"custom","font":"var(--font-primary--family)","font_size":"","line_height":"normal","letter_spacing":"normal","case":"none","wrap":"pretty","color":"","background":false,"background_color":"#00000026","corner_radius":0,"padding-block-start":0,"padding-block-end":0,"padding-inline-start":0,"padding-inline-end":0},"blocks":{}},"static-product-card":{"type":"_product-card","name":"t:names.product_card","static":true,"settings":{"product_card_gap":8,"inherit_color_scheme":true,"color_scheme":"","border":"none","border_width":1,"border_opacity":100,"border_radius":0,"padding-block-start":0,"padding-block-end":8,"padding-inline-start":0,"padding-inline-end":0},"blocks":{"product_card_gallery_DNizbJ":{"type":"_product-card-gallery","name":"t:names.product_card_media","settings":{"image_ratio":"portrait","border":"none","border_width":1,"border_opacity":100,"border_radius":0,"padding-block-start":0,"padding-block-end":0,"padding-inline-start":0,"padding-inline-end":0},"blocks":{}},"product_title_M7MJkb":{"type":"product-title","name":"t:names.product_title","settings":{"width":"100%","max_width":"narrow","alignment":"center","type_preset":"custom","font":"var(--font-body--family)","font_size":"0.75rem","line_height":"normal","letter_spacing":"tight","case":"none","wrap":"pretty","color":"var(--color-foreground)","background":false,"background_color":"#00000026","corner_radius":0,"padding-block-start":4,"padding-block-end":0,"padding-inline-start":0,"padding-inline-end":0},"blocks":{}},"price_gLWgA6":{"type":"price","settings":{"discount_badge_bg":"#a32626","show_sale_price_first":true,"show_installments":false,"show_tax_info":false,"type_preset":"custom","width":"100%","alignment":"center","font":"var(--font-body--family)","font_size":"0.875rem","line_height":"normal","letter_spacing":"normal","case":"uppercase","color":"var(--color-foreground)","padding-block-start":0,"padding-block-end":0,"padding-inline-start":0,"padding-inline-end":0},"blocks":{}}},"block_order":["product_card_gallery_DNizbJ","product_title_M7MJkb","price_gLWgA6"]}},"block_order":["ai_gen_block_78e2178_jxW8zL","text_cbcgyb"],"name":"t:names.product_recommendations","settings":{"product":"{{ product }}","recommendation_type":"related","layout_type":"grid","carousel_on_mobile":false,"max_products":8,"columns":8,"mobile_columns":"2","columns_gap":12,"rows_gap":24,"icons_style":"arrow","icons_shape":"none","section_width":"page-width","gap":28,"color_scheme":"scheme-1","padding-block-start":5,"padding-block-end":0}},"blocks_3GbCGK":{"type":"_blocks","blocks":{"ai_gen_block_78e2178_3KqF36":{"type":"ai_gen_block_78e2178","name":"Title block","settings":{"heading":"Styled By You","font_size":24,"font_size_mobile":16,"text_transform":"none","letter_spacing":0,"alignment":"center","text_color":"#ffffff","background_color":"#333333","padding_top":12,"padding_bottom":12,"padding_horizontal":0,"padding_top_mobile":12,"padding_bottom_mobile":12,"padding_horizontal_mobile":0},"blocks":{}},"instafeed_app_block_bFWHEi":{"type":"shopify:\/\/apps\/instafeed\/blocks\/app-block\/c447db20-095d-4a10-9725-b5977662c9d5","settings":{"title":"","title_color":"","title_size_v2":0,"alignment":"center","instafeed_margin_top":0,"instafeed_margin_bottom":0,"instafeed_margin_sides":0,"show_instagram_link":false,"link_alignment":"left","link_color":"#000000","background_color":"","feed_id":"","html_area":""}}},"block_order":["ai_gen_block_78e2178_3KqF36","instafeed_app_block_bFWHEi"],"settings":{"content_direction":"column","vertical_on_mobile":true,"horizontal_alignment":"flex-start","vertical_alignment":"center","align_baseline":false,"horizontal_alignment_flex_direction_column":"flex-start","vertical_alignment_flex_direction_column":"center","gap":12,"section_width":"page-width","section_height":"","section_height_custom":50,"color_scheme":"","background_media":"none","video_position":"cover","background_image_position":"cover","border":"none","border_width":1,"border_opacity":100,"border_radius":0,"toggle_overlay":false,"overlay_color":"#00000026","overlay_style":"solid","gradient_direction":"to top","padding-block-start":0,"padding-block-end":0}},"recently_viewed_tmDNaC":{"type":"recently-viewed","name":"Recently viewed products","settings":{"heading":"Recently viewed","heading_font_size":28,"max_products":5,"empty_message":"No recently viewed products","layout_type":"grid","carousel_on_mobile":false,"columns":6,"mobile_columns":"2","columns_gap":12,"rows_gap":12,"image_ratio":"portrait","image_border":"none","image_border_width":1,"image_border_radius":0,"title_preset":"h4","title_font":"var(--font-body--family)","title_size":"0.875rem","title_alignment":"center","price_preset":"paragraph","price_font":"var(--font-body--family)","price_size":"0.875rem","price_alignment":"center","section_width":"page-width","gap":28,"color_scheme":"","padding-block-start":48,"padding-block-end":48,"padding-inline-start":0,"padding-inline-end":0,"mobile-padding-block-start":36,"mobile-padding-block-end":36,"mobile-padding-inline-start":16,"mobile-padding-inline-end":16}}},"order":["main","blocks_PzEKUJ","17764266138876d846","1777368950ce942549","product_recommendations_qggXJq","blocks_3GbCGK","recently_viewed_tmDNaC"]}